Workbook

Sheet Tiers de Precio
A1: Tiers de precio
A2: Ecuador está dolarizado: el precio en USD es el mismo local e internacional (sin fricción de cambio).
A4: Tier | B4: Umbral valor acumulado ($/mes) | C4: Precio ($/mes · EC = Intl) | D4: Qué incluye
A5: Gratis | B5: 0 | C5: 0 | D5: Resuelve el trabajo central lo suficiente para adoptar. Sin login, sin barrera: es tu carta de presentación.
A6: Semilla | B6: 1.5 | C6: 0.99 | D6: El desbloqueo no-brainer: guardar, exportar, sin límites. Precio de 'ni lo pienses'.
A7: Pro | B7: 4 | C7: 2.99 | D7: IA explicativa, lotes, reportes PDF para tesis, gráficos. Para quien ya vive del producto.
A8: Institucional | B8: 10 | C8: 19.99 | D8: Licencia por curso: el docente paga una vez por su clase (10-30 alumnos). El salto exponencial.
A10: Celdas amarillas = tú las editas (umbrales y precios). El Registro de Valor lee estos umbrales para sugerir el tier automáticamente.

Sheet Registro de Valor
A1: Registro de valor · cada commit suma hacia un precio justificado
A2: Empiezas en $0. Cada incremento aporta valor mensual justificado (de milésimas a décimas). El acumulado desbloquea tiers.
A4: ID (commit/ticket) | B4: Fecha | C4: Incremento construido | D4: Audiencia | E4: Tipo | F4: Valor $/mes justificado | G4: Acumulado $/mes | H4: Tier desbloqueado | I4: Precio sugerido $/mes | J4: Enlace commit | K4: Notas
A5: FUND-000 | B5: 2026-07-28 | C5: Repo + landing con lista de espera | D5: Todas | E5: infra | F5: 0 | G5: =SUM($F$5:F5) | H5: =IF(G5>='Tiers de Precio'!$B$8,'Tiers de Precio'!$A$8,IF(G5>='Tiers de Precio'!$B$7,'Tiers de Precio'!$A$7,IF(G5>='Tiers de Precio'!$B$6,'Tiers de Precio'!$A$6,'Tiers de Precio'!$A$5))) | I5: =IF(G5>='Tiers de Precio'!$B$8,'Tiers de Precio'!$C$8,IF(G5>='Tiers de Precio'!$B$7,'Tiers de Precio'!$C$7,IF(G5>='Tiers de Precio'!$B$6,'Tiers de Precio'!$C$6,'Tiers de Precio'!$C$5)))
A6: STAT-001 | C6: Subir CSV y describir datos (media, sd, n) | D6: Todas | E6: core | F6: 0.3 | G6: =SUM($F$5:F6) | H6: =IF(G6>='Tiers de Precio'!$B$8,'Tiers de Precio'!$A$8,IF(G6>='Tiers de Precio'!$B$7,'Tiers de Precio'!$A$7,IF(G6>='Tiers de Precio'!$B$6,'Tiers de Precio'!$A$6,'Tiers de Precio'!$A$5))) | I6: =IF(G6>='Tiers de Precio'!$B$8,'Tiers de Precio'!$C$8,IF(G6>='Tiers de Precio'!$B$7,'Tiers de Precio'!$C$7,IF(G6>='Tiers de Precio'!$B$6,'Tiers de Precio'!$C$6,'Tiers de Precio'!$C$5)))
A7: STAT-002 | C7: Selector ¿qué test usar? (árbol de decisión) | D7: Todas | E7: killer | F7: 1.2 | G7: =SUM($F$5:F7) | H7: =IF(G7>='Tiers de Precio'!$B$8,'Tiers de Precio'!$A$8,IF(G7>='Tiers de Precio'!$B$7,'Tiers de Precio'!$A$7,IF(G7>='Tiers de Precio'!$B$6,'Tiers de Precio'!$A$6,'Tiers de Precio'!$A$5))) | I7: =IF(G7>='Tiers de Precio'!$B$8,'Tiers de Precio'!$C$8,IF(G7>='Tiers de Precio'!$B$7,'Tiers de Precio'!$C$7,IF(G7>='Tiers de Precio'!$B$6,'Tiers de Precio'!$C$6,'Tiers de Precio'!$C$5)))
A8: STAT-003 | C8: Corre t-test / Wilcoxon / chi² con resultado | D8: Todas | E8: core | F8: 0.6 | G8: =SUM($F$5:F8) | H8: =IF(G8>='Tiers de Precio'!$B$8,'Tiers de Precio'!$A$8,IF(G8>='Tiers de Precio'!$B$7,'Tiers de Precio'!$A$7,IF(G8>='Tiers de Precio'!$B$6,'Tiers de Precio'!$A$6,'Tiers de Precio'!$A$5))) | I8: =IF(G8>='Tiers de Precio'!$B$8,'Tiers de Precio'!$C$8,IF(G8>='Tiers de Precio'!$B$7,'Tiers de Precio'!$C$7,IF(G8>='Tiers de Precio'!$B$6,'Tiers de Precio'!$C$6,'Tiers de Precio'!$C$5)))
A9: STAT-004 | C9: Chequeo de supuestos (normalidad, varianzas) | D9: Todas | E9: feature | F9: 0.25 | G9: =SUM($F$5:F9) | H9: =IF(G9>='Tiers de Precio'!$B$8,'Tiers de Precio'!$A$8,IF(G9>='Tiers de Precio'!$B$7,'Tiers de Precio'!$A$7,IF(G9>='Tiers de Precio'!$B$6,'Tiers de Precio'!$A$6,'Tiers de Precio'!$A$5))) | I9: =IF(G9>='Tiers de Precio'!$B$8,'Tiers de Precio'!$C$8,IF(G9>='Tiers de Precio'!$B$7,'Tiers de Precio'!$C$7,IF(G9>='Tiers de Precio'!$B$6,'Tiers de Precio'!$C$6,'Tiers de Precio'!$C$5)))
A10: STAT-005 | C10: Explicación en lenguaje claro (LLM) | D10: Todas | E10: killer | F10: 1 | G10: =SUM($F$5:F10) | H10: =IF(G10>='Tiers de Precio'!$B$8,'Tiers de Precio'!$A$8,IF(G10>='Tiers de Precio'!$B$7,'Tiers de Precio'!$A$7,IF(G10>='Tiers de Precio'!$B$6,'Tiers de Precio'!$A$6,'Tiers de Precio'!$A$5))) | I10: =IF(G10>='Tiers de Precio'!$B$8,'Tiers de Precio'!$C$8,IF(G10>='Tiers de Precio'!$B$7,'Tiers de Precio'!$C$7,IF(G10>='Tiers de Precio'!$B$6,'Tiers de Precio'!$C$6,'Tiers de Precio'!$C$5)))
A11: STAT-006 | C11: Exportar reporte PDF para anexar a la tesis | D11: Todas | E11: feature | F11: 0.4 | G11: =SUM($F$5:F11) | H11: =IF(G11>='Tiers de Precio'!$B$8,'Tiers de Precio'!$A$8,IF(G11>='Tiers de Precio'!$B$7,'Tiers de Precio'!$A$7,IF(G11>='Tiers de Precio'!$B$6,'Tiers de Precio'!$A$6,'Tiers de Precio'!$A$5))) | I11: =IF(G11>='Tiers de Precio'!$B$8,'Tiers de Precio'!$C$8,IF(G11>='Tiers de Precio'!$B$7,'Tiers de Precio'!$C$7,IF(G11>='Tiers de Precio'!$B$6,'Tiers de Precio'!$C$6,'Tiers de Precio'!$C$5)))
A12: STAT-007 | C12: Gráficos listos para tesis (APA) | D12: Todas | E12: feature | F12: 0.3 | G12: =SUM($F$5:F12) | H12: =IF(G12>='Tiers de Precio'!$B$8,'Tiers de Precio'!$A$8,IF(G12>='Tiers de Precio'!$B$7,'Tiers de Precio'!$A$7,IF(G12>='Tiers de Precio'!$B$6,'Tiers de Precio'!$A$6,'Tiers de Precio'!$A$5))) | I12: =IF(G12>='Tiers de Precio'!$B$8,'Tiers de Precio'!$C$8,IF(G12>='Tiers de Precio'!$B$7,'Tiers de Precio'!$C$7,IF(G12>='Tiers de Precio'!$B$6,'Tiers de Precio'!$C$6,'Tiers de Precio'!$C$5)))
A13: STAT-008 | C13: Cuentas de usuario + historial | D13: Todas | E13: infra | F13: 0.2 | G13: =SUM($F$5:F13) | H13: =IF(G13>='Tiers de Precio'!$B$8,'Tiers de Precio'!$A$8,IF(G13>='Tiers de Precio'!$B$7,'Tiers de Precio'!$A$7,IF(G13>='Tiers de Precio'!$B$6,'Tiers de Precio'!$A$6,'Tiers de Precio'!$A$5))) | I13: =IF(G13>='Tiers de Precio'!$B$8,'Tiers de Precio'!$C$8,IF(G13>='Tiers de Precio'!$B$7,'Tiers de Precio'!$C$7,IF(G13>='Tiers de Precio'!$B$6,'Tiers de Precio'!$C$6,'Tiers de Precio'!$C$5)))
A14: STAT-009 | C14: Panel docente (modo institucional) | D14: Docentes | E14: growth | F14: 0.6 | G14: =SUM($F$5:F14) | H14: =IF(G14>='Tiers de Precio'!$B$8,'Tiers de Precio'!$A$8,IF(G14>='Tiers de Precio'!$B$7,'Tiers de Precio'!$A$7,IF(G14>='Tiers de Precio'!$B$6,'Tiers de Precio'!$A$6,'Tiers de Precio'!$A$5))) | I14: =IF(G14>='Tiers de Precio'!$B$8,'Tiers de Precio'!$C$8,IF(G14>='Tiers de Precio'!$B$7,'Tiers de Precio'!$C$7,IF(G14>='Tiers de Precio'!$B$6,'Tiers de Precio'!$C$6,'Tiers de Precio'!$C$5)))
E15: TOTAL | F15: =SUM(F5:F14) | G15: =G14 | H15: =IF(G14>='Tiers de Precio'!$B$8,'Tiers de Precio'!$A$8,IF(G14>='Tiers de Precio'!$B$7,'Tiers de Precio'!$A$7,IF(G14>='Tiers de Precio'!$B$6,'Tiers de Precio'!$A$6,'Tiers de Precio'!$A$5))) | I15: =IF(G14>='Tiers de Precio'!$B$8,'Tiers de Precio'!$C$8,IF(G14>='Tiers de Precio'!$B$7,'Tiers de Precio'!$C$7,IF(G14>='Tiers de Precio'!$B$6,'Tiers de Precio'!$C$6,'Tiers de Precio'!$C$5)))
A17: Leyenda: celdas AMARILLAS (col. 'Valor $/mes') = tú las editas por cada commit. Columnas grises (Acumulado, Tier, Precio) se calculan solas.
A18: Tipos: fix (0.005–0.05) · feature (0.10–0.40) · core (0.40–0.80) · killer (0.80–2.0) · infra/growth (según impacto).
A19: Regla: el valor NO es tu esfuerzo, es lo que le AHORRAS al usuario. 2 horas de estadística de tesis ahorradas valen mucho más que tu tiempo de codear.

Sheet Modelo de Crecimiento
A1: Modelo de crecimiento del precio
A2: Cómo evoluciona el valor acumulado según construyas lineal (constante) o exponencial (efectos de red).
A4: Aporte lineal por feature ($): | B4: 0.35
A5: Aporte inicial exponencial ($): | B5: 0.1
A6: Factor exponencial (×): | B6: 1.3
A8: Feature # | B8: Aporte lineal | C8: Acum. lineal | D8: Aporte exponencial | E8: Acum. exponencial | F8: Tier (por exp.)
A9: 0 | B9: =$B$4 | C9: =B9 | D9: =$B$5 | E9: =D9 | F9: =IF(E9>='Tiers de Precio'!$B$8,'Tiers de Precio'!$A$8,IF(E9>='Tiers de Precio'!$B$7,'Tiers de Precio'!$A$7,IF(E9>='Tiers de Precio'!$B$6,'Tiers de Precio'!$A$6,'Tiers de Precio'!$A$5)))
A10: 1 | B10: =$B$4 | C10: =C9+B10 | D10: =D9*$B$6 | E10: =E9+D10 | F10: =IF(E10>='Tiers de Precio'!$B$8,'Tiers de Precio'!$A$8,IF(E10>='Tiers de Precio'!$B$7,'Tiers de Precio'!$A$7,IF(E10>='Tiers de Precio'!$B$6,'Tiers de Precio'!$A$6,'Tiers de Precio'!$A$5)))
A11: 2 | B11: =$B$4 | C11: =C10+B11 | D11: =D10*$B$6 | E11: =E10+D11 | F11: =IF(E11>='Tiers de Precio'!$B$8,'Tiers de Precio'!$A$8,IF(E11>='Tiers de Precio'!$B$7,'Tiers de Precio'!$A$7,IF(E11>='Tiers de Precio'!$B$6,'Tiers de Precio'!$A$6,'Tiers de Precio'!$A$5)))
A12: 3 | B12: =$B$4 | C12: =C11+B12 | D12: =D11*$B$6 | E12: =E11+D12 | F12: =IF(E12>='Tiers de Precio'!$B$8,'Tiers de Precio'!$A$8,IF(E12>='Tiers de Precio'!$B$7,'Tiers de Precio'!$A$7,IF(E12>='Tiers de Precio'!$B$6,'Tiers de Precio'!$A$6,'Tiers de Precio'!$A$5)))
A13: 4 | B13: =$B$4 | C13: =C12+B13 | D13: =D12*$B$6 | E13: =E12+D13 | F13: =IF(E13>='Tiers de Precio'!$B$8,'Tiers de Precio'!$A$8,IF(E13>='Tiers de Precio'!$B$7,'Tiers de Precio'!$A$7,IF(E13>='Tiers de Precio'!$B$6,'Tiers de Precio'!$A$6,'Tiers de Precio'!$A$5)))
A14: 5 | B14: =$B$4 | C14: =C13+B14 | D14: =D13*$B$6 | E14: =E13+D14 | F14: =IF(E14>='Tiers de Precio'!$B$8,'Tiers de Precio'!$A$8,IF(E14>='Tiers de Precio'!$B$7,'Tiers de Precio'!$A$7,IF(E14>='Tiers de Precio'!$B$6,'Tiers de Precio'!$A$6,'Tiers de Precio'!$A$5)))
A15: 6 | B15: =$B$4 | C15: =C14+B15 | D15: =D14*$B$6 | E15: =E14+D15 | F15: =IF(E15>='Tiers de Precio'!$B$8,'Tiers de Precio'!$A$8,IF(E15>='Tiers de Precio'!$B$7,'Tiers de Precio'!$A$7,IF(E15>='Tiers de Precio'!$B$6,'Tiers de Precio'!$A$6,'Tiers de Precio'!$A$5)))
A16: 7 | B16: =$B$4 | C16: =C15+B16 | D16: =D15*$B$6 | E16: =E15+D16 | F16: =IF(E16>='Tiers de Precio'!$B$8,'Tiers de Precio'!$A$8,IF(E16>='Tiers de Precio'!$B$7,'Tiers de Precio'!$A$7,IF(E16>='Tiers de Precio'!$B$6,'Tiers de Precio'!$A$6,'Tiers de Precio'!$A$5)))
A17: 8 | B17: =$B$4 | C17: =C16+B17 | D17: =D16*$B$6 | E17: =E16+D17 | F17: =IF(E17>='Tiers de Precio'!$B$8,'Tiers de Precio'!$A$8,IF(E17>='Tiers de Precio'!$B$7,'Tiers de Precio'!$A$7,IF(E17>='Tiers de Precio'!$B$6,'Tiers de Precio'!$A$6,'Tiers de Precio'!$A$5)))
A18: 9 | B18: =$B$4 | C18: =C17+B18 | D18: =D17*$B$6 | E18: =E17+D18 | F18: =IF(E18>='Tiers de Precio'!$B$8,'Tiers de Precio'!$A$8,IF(E18>='Tiers de Precio'!$B$7,'Tiers de Precio'!$A$7,IF(E18>='Tiers de Precio'!$B$6,'Tiers de Precio'!$A$6,'Tiers de Precio'!$A$5)))
A19: 10 | B19: =$B$4 | C19: =C18+B19 | D19: =D18*$B$6 | E19: =E18+D19 | F19: =IF(E19>='Tiers de Precio'!$B$8,'Tiers de Precio'!$A$8,IF(E19>='Tiers de Precio'!$B$7,'Tiers de Precio'!$A$7,IF(E19>='Tiers de Precio'!$B$6,'Tiers de Precio'!$A$6,'Tiers de Precio'!$A$5)))
A20: 11 | B20: =$B$4 | C20: =C19+B20 | D20: =D19*$B$6 | E20: =E19+D20 | F20: =IF(E20>='Tiers de Precio'!$B$8,'Tiers de Precio'!$A$8,IF(E20>='Tiers de Precio'!$B$7,'Tiers de Precio'!$A$7,IF(E20>='Tiers de Precio'!$B$6,'Tiers de Precio'!$A$6,'Tiers de Precio'!$A$5)))
A21: 12 | B21: =$B$4 | C21: =C20+B21 | D21: =D20*$B$6 | E21: =E20+D21 | F21: =IF(E21>='Tiers de Precio'!$B$8,'Tiers de Precio'!$A$8,IF(E21>='Tiers de Precio'!$B$7,'Tiers de Precio'!$A$7,IF(E21>='Tiers de Precio'!$B$6,'Tiers de Precio'!$A$6,'Tiers de Precio'!$A$5)))
... A24: 15 | B24: =$B$4 | C24: =C23+B24 | D24: =D23*$B$6 | E24: =E23+D24 | F24: =IF(E24>='Tiers de Precio'!$B$8,'Tiers de Precio'!$A$8,IF(E24>='Tiers de Precio'!$B$7,'Tiers de Precio'!$A$7,IF(E24>='Tiers de Precio'!$B$6,'Tiers de Precio'!$A$6,'Tiers de Precio'!$A$5)))
A26: Lectura: lo lineal es constante y predecible; lo exponencial arranca lento pero acelera con integraciones y boca-a-boca. Edita las 3 celdas amarillas para ver tu curva.

Sheet Cómo usar y cotizar
A1: Cómo usar este modelo y cómo cotizar valor
A2: La filosofía: el precio refleja el valor entregado, no las horas trabajadas.
B4: 1 · La regla fundacional
B5: Empiezas en $0 porque aún no hay nada. Cada commit/feature aporta valor mensual justificado que se acumula en el Registro de Valor. Cuando el acumulado cruza un umbral, desbloqueas un tier de precio. Así el precio nunca es arbitrario: siempre está respaldado por lo que el producto ya hace.
B7: 2 · El valor NO es tu esfuerzo
B8: Cotiza por lo que le AHORRAS al usuario, no por lo que te costó construir. Si tu herramienta le ahorra a un tesista 3 horas de pelear con estadística, eso vale mucho más que los $2/mes que cobras. Esa brecha (valor entregado ≫ precio) es lo que hace que pagar se sienta una ganga.
B10: 3 · Ecuador = Internacional (misma cifra)
B11: Ecuador usa el dólar, así que tu precio en USD es idéntico local e internacionalmente. Un precio pensado para Ecuador ($1.99–$4.99) se lee como barato afuera: eso REDUCE fricción y te da ventaja, no la quita. No conviertas monedas; cotiza en USD y listo.
B13: 4 · Cuándo subir el precio
B14: Sube cuando: (a) el acumulado cruza el siguiente umbral, (b) los usuarios usan el producto repetidamente (retención), o (c) agregas una feature 'killer' que ahorra tiempo real. Sube a los usuarios NUEVOS primero; a los antiguos respétales el precio un tiempo (genera lealtad).
B16: 5 · Lineal vs exponencial
B17: Al inicio, crece lineal: cada feature suma un poco. Cuando aparezcan integraciones, boca-a-boca o modo institucional (varios usuarios por venta), el valor crece exponencial. La pestaña 'Modelo de Crecimiento' te deja simular ambas curvas editando 3 celdas.
B19: 6 · Cómo lo usas en el día a día
B20: Cada vez que cierres un ticket con valor para el usuario: añade una fila al Registro de Valor con su aporte estimado, commitea, y anota en tu Bitácora. El modelo te dirá en qué tier estás y qué precio está justificado pedir. Es tu brújula de precio, respaldada por evidencia.
... B29: Estos valores son estimaciones para guiarte, no una ciencia exacta. El precio REAL lo valida el mercado: si nadie paga tu tier, el valor percibido es menor al que estimaste (mejora la feature); si pagan sin dudar, subestimaste (puedes subir). El modelo te orienta; los usuarios deciden.
